<?xml version="1.0" encoding="UTF-8"?>
<objects serializationModel="Studio.01.10.00">
    <object class="AudioFile" id="{fb9da4b2-5294-434d-b8d7-9a9d136eed35}">
        <property name="assetPath">
            <value>Tank_ambience/Tank_scatter_21.wav</value>
        </property>
        <property name="frequencyInKHz">
            <value>48</value>
        </property>
        <property name="channelCount">
            <value>2</value>
        </property>
        <property name="length">
            <value>0.82327083333333329</value>
        </property>
        <relationship name="masterAssetFolder">
            <destination>{8f0ed7f5-d3e9-4f5e-8f68-21dc68cfb3a2}</destination>
        </relationship>
    </object>
</objects>
